sanja.py
sanja-1.0.5.dist-info/LICENSE
sanja-1.0.5.dist-info/METADATA
sanja-1.0.5.dist-info/WHEEL
sanja-1.0.5.dist-info/top_level.txt
sanja-1.0.5.dist-info/RECORD
