Metadata-Version: 2.1
Name: sanja
Version: 1.0.5
Summary: This module aims to make bringing Jinja templates to Sanic to be easy.
Home-page: https://github.com/tomaszdrozdz/sanja
Author: tomaszdrozdz
Author-email: tomasz.drozdz.1@protonmail.com
License: GPLv3
Platform: UNKNOWN
Classifier: License :: OSI Approved :: GNU General Public License v3 (GPLv3)
Classifier: Programming Language :: Python :: 3.8
Requires-Python: >=3.8
Requires-Dist: sanic
Requires-Dist: jinja2
